COPYING
MANIFEST.in
README.rst
buildout.cfg
develop.cfg
requirements.txt
setup.py
version.txt
bob/__init__.py
bob.db.scface.egg-info/PKG-INFO
bob.db.scface.egg-info/SOURCES.txt
bob.db.scface.egg-info/dependency_links.txt
bob.db.scface.egg-info/entry_points.txt
bob.db.scface.egg-info/not-zip-safe
bob.db.scface.egg-info/requires.txt
bob.db.scface.egg-info/top_level.txt
bob/db/__init__.py
bob/db/scface/__init__.py
bob/db/scface/create.py
bob/db/scface/driver.py
bob/db/scface/models.py
bob/db/scface/query.py
bob/db/scface/scface_annotations.txt
bob/db/scface/test.py
doc/conf.py
doc/guide.rst
doc/index.rst
doc/py_api.rst