Metadata-Version: 1.1
Name: bob.db.scface
Version: 2.1.6
Summary: SCface Database Access API for Bob
Home-page: https://gitlab.idiap.ch/bob/bob.db.scface
Author: Laurent El Shafey
Author-email: laurent.el-shafey@idiap.ch
License: BSD
Keywords: face recognition,bob,bob.db,SCface
Platform: UNKNOWN
Classifier: Framework :: Bob
Classifier: Development Status :: 4 - Beta
Classifier: Environment :: Console
Classifier: Intended Audience :: Developers
Classifier: Intended Audience :: Education
Classifier: Intended Audience :: Science/Research
Classifier: License :: OSI Approved :: BSD License
Classifier: Natural Language :: English
Classifier: Programming Language :: Python
Classifier: Programming Language :: Python :: 3
Classifier: Topic :: Scientific/Engineering :: Artificial Intelligence
Classifier: Topic :: Database :: Front-Ends
